HW2/decoder.v
// Decoder circuit

// define gates with delays
`define AND and #50
`define OR or #50
`define NOT not #50

module behavioralDecoder
(
    output out0, out1, out2, out3,
    input address0, address1,
    input enable
);
    // Uses concatenation and shift operators
    assign {out3,out2,out1,out0}=enable<<{address1,address0};
endmodule


module structuralDecoder
(
    output out0, out1, out2, out3,
    input address0, address1,
    input enable
);
    
    wire con_0; wire con_1; wire con_2; wire con_3;
    wire tc0; wire tc1; wire tc2; wire tc3;    
    wire n0; wire n1;

    // Inverted inputs
    `NOT not_0 (n0, address0);
    `NOT not_1 (n1, address1);

    // Determine which output is connected to enable
    `AND connected_0 (con_0, n0, n1);
    `AND connected_1 (con_1, address0, n1);
    `AND connected_2 (con_2, n0, address1);
    `AND connected_3 (con_3, address0, address1);

    // Set output conditions
    `AND out0_is_true (out0, con_0, enable);
    `AND out1_is_true (out1, con_1, enable);
    `AND out2_is_true (out2, con_2, enable);
    `AND out3_is_true (out3, con_3, enable);
    
endmodule

HW2/decoder.t.v
// Decoder testbench

`timescale 1 ns / 1 ps
`include "decoder.v"

module testDecoder (); 
    reg addr0, addr1;
    reg enable;
    wire out0,out1,out2,out3;
    wire out4,out5,out6,out7;

    behavioralDecoder decoder (out0,out1,out2,out3,addr0,addr1,enable);
    structuralDecoder my_decoder (out4,out5,out6,out7,addr0,addr1,enable); // Swap after testing

    initial begin

    $dumpfile("decoder.vcd");
    $dumpvars();

    $display("En A0 A1| Ben's Output | My Output | Expected Output");
    enable=0;addr0=0;addr1=0; #1000 
    $display("%b  %b  %b |   %b  %b  %b  %b |   %b %b %b %b | All false ", enable, addr0, addr1, out0, out1, out2, out3, out4, out5, out6, out7);
    enable=0;addr0=1;addr1=0; #1000
    $display("%b  %b  %b |   %b  %b  %b  %b |   %b %b %b %b | All false ", enable, addr0, addr1, out0, out1, out2, out3, out4, out5, out6, out7);
    enable=0;addr0=0;addr1=1; #1000 
    $display("%b  %b  %b |   %b  %b  %b  %b |   %b %b %b %b | All false ", enable, addr0, addr1, out0, out1, out2, out3, out4, out5, out6, out7);
    enable=0;addr0=1;addr1=1; #1000 
    $display("%b  %b  %b |   %b  %b  %b  %b |   %b %b %b %b | All false ", enable, addr0, addr1, out0, out1, out2, out3, out4, out5, out6, out7);
    enable=1;addr0=0;addr1=0; #1000 
    $display("%b  %b  %b |   %b  %b  %b  %b |   %b %b %b %b | O0 Only   ", enable, addr0, addr1, out0, out1, out2, out3, out4, out5, out6, out7);
    enable=1;addr0=1;addr1=0; #1000 
    $display("%b  %b  %b |   %b  %b  %b  %b |   %b %b %b %b | O1 Only   ", enable, addr0, addr1, out0, out1, out2, out3, out4, out5, out6, out7);
    enable=1;addr0=0;addr1=1; #1000 
    $display("%b  %b  %b |   %b  %b  %b  %b |   %b %b %b %b | O2 Only   ", enable, addr0, addr1, out0, out1, out2, out3, out4, out5, out6, out7);
    enable=1;addr0=1;addr1=1; #1000 
    $display("%b  %b  %b |   %b  %b  %b  %b |   %b %b %b %b | O3 Only   ", enable, addr0, addr1, out0, out1, out2, out3, out4, out5, out6, out7);
    $finish();
    end

endmodule

HW2/decoder.vcd
$date
	Thu Sep 20 23:55:30 2018
$end
$version
	Icarus Verilog
$end
$timescale
	1ps
$end
$scope module testDecoder $end
$var wire 1 ! out7 $end
$var wire 1 " out6 $end
$var wire 1 # out5 $end
$var wire 1 $ out4 $end
$var wire 1 % out3 $end
$var wire 1 & out2 $end
$var wire 1 ' out1 $end
$var wire 1 ( out0 $end
$var reg 1 ) addr0 $end
$var reg 1 * addr1 $end
$var reg 1 + enable $end
$scope module decoder $end
$var wire 1 ) address0 $end
$var wire 1 * address1 $end
$var wire 1 + enable $end
$var wire 1 % out3 $end
$var wire 1 & out2 $end
$var wire 1 ' out1 $end
$var wire 1 ( out0 $end
$upscope $end
$scope module my_decoder $end
$var wire 1 ) address0 $end
$var wire 1 * address1 $end
$var wire 1 , con_0 $end
$var wire 1 - con_1 $end
$var wire 1 . con_2 $end
$var wire 1 / con_3 $end
$var wire 1 + enable $end
$var wire 1 0 n0 $end
$var wire 1 1 n1 $end
$var wire 1 $ out0 $end
$var wire 1 # out1 $end
$var wire 1 " out2 $end
$var wire 1 ! out3 $end
$upscope $end
$upscope $end
$enddefinitions $end
#0
$dumpvars
x1
x0
x/
x.
x-
x,
0+
0*
0)
0(
0'
0&
0%
x$
x#
x"
x!
$end
#50000
11
10
0!
0"
0#
0$
0/
0.
0-
#100000
1,
#1000000
1)
#1050000
00
1-
#1100000
0,
#2000000
1*
0)
#2050000
01
10
0-
#2100000
1.
#3000000
1)
#3050000
00
1/
#3100000
0.
#4000000
1(
0*
0)
1+
#4050000
11
10
0/
1!
#4100000
1,
0!
#4150000
1$
#5000000
0(
1'
1)
#5050000
00
1-
#5100000
0,
1#
#5150000
0$
#6000000
1&
0'
1*
0)
#6050000
01
10
0-
#6100000
1.
0#
#6150000
1"
#7000000
0&
1%
1)
#7050000
00
1/
#7100000
0.
1!
#7150000
0"
